[
	{
		"name": "数据结构308",
		"id": 0,
		"classes": 2020211308,
		"week": [
			true,
			false,
			false,
			false,
			false,
			false,
			false
		],
		"time": [
			[
				"08:00",
				"09:35"
			],
			[],
			[],
			[],
			[],
			[],
			[]
		],
		"place": [
			131,
			"N113"
		],
		"teacher": "李老师",
		"info": [
			"数据结构课程",
			"无",
			"18周周四9:00-12:00"
		]
	},
	{
		"name": "数据逻辑310",
		"id": 1,
		"classes": 2020211310,
		"week": [
			false,
			true,
			false,
			false,
			false,
			false,
			false
		],
		"time": [
			[],
			[
				"08:00",
				"09:35"
			],
			[],
			[],
			[],
			[],
			[]
		],
		"place": [
			131,
			"S117"
		],
		"teacher": "刘老师",
		"info": [
			"无",
			"无",
			"无"
		]
	},
	{
		"name": "计算机系统308",
		"id": 2,
		"classes": 2020211308,
		"week": [
			false,
			false,
			true,
			false,
			false,
			false,
			false
		],
		"time": [
			[],
			[],
			[
				"13:00",
				"14:35"
			],
			[],
			[],
			[],
			[]
		],
		"place": [
			131,
			"S208"
		],
		"teacher": "老师",
		"info": [
			"无",
			"无",
			"无"
		]
	},
	{
		"name": "计算机系统课程设计309",
		"id": 3,
		"classes": 2020211309,
		"week": [
			false,
			true,
			false,
			false,
			false,
			false,
			false
		],
		"time": [
			[],
			[
				"09:50",
				"11:25"
			],
			[],
			[],
			[],
			[],
			[]
		],
		"place": [
			21,
			"208"
		],
		"teacher": "大师傅",
		"info": [
			"无",
			"无",
			"无"
		]
	},
	{
		"name": "组成原理308",
		"id": 4,
		"classes": 2020211308,
		"week": [
			false,
			false,
			false,
			true,
			false,
			false,
			false
		],
		"time": [
			[],
			[],
			[],
			[
				"08:00",
				"09:35"
			],
			[],
			[],
			[]
		],
		"place": [
			131,
			"N209"
		],
		"teacher": "丁老师",
		"info": [
			"",
			"",
			""
		]
	},
	{
		"name": "编译原理310",
		"id": 5,
		"classes": 2020211310,
		"week": [
			false,
			false,
			true,
			false,
			false,
			false,
			false
		],
		"time": [
			[],
			[],
			[
				"13:00",
				"14:35"
			],
			[],
			[],
			[],
			[]
		],
		"place": [
			20,
			"313"
		],
		"teacher": "林老师",
		"info": [
			"无",
			"无",
			"无"
		]
	}
]